CHANGELOG.rst
MANIFEST.in
README.rst
setup.py
autoloads/__init__.py
autoloads/app.py
autoloads/basehandler.py
autoloads/dbs.py
autoloads.egg-info/PKG-INFO
autoloads.egg-info/SOURCES.txt
autoloads.egg-info/dependency_links.txt
autoloads.egg-info/not-zip-safe
autoloads.egg-info/pbr.json
autoloads.egg-info/requires.txt
autoloads.egg-info/top_level.txt
autoloads/utils/__init__.py
autoloads/utils/base.py
autoloads/utils/dbhelper.py
autoloads/utils/dbpipe.py
autoloads/utils/dbutils.py
demo/__init__.py
demo/config.py
demo/main.py
demo/models/__init__.py
demo/models/base.py
demo/models/models.py
demo/utils/__init__.py
demo/utils/options_parse.py
demo/views/__init__.py
demo/views/views.py