Metadata-Version: 1.1
Name: autoloads
Version: 0.2.2.3
Summary: python web and databases's tools.
Home-page: https://github.com/wujuguang/autoloads.git
Author: wuxiaoge
Author-email: returnliu@gmail.com
License: MIT License
Keywords: autoloads
Platform: any
Classifier: Development Status :: 4 - Beta
Classifier: Environment :: Console
Classifier: Environment :: Web Environment
Classifier: Intended Audience :: Developers
Classifier: Programming Language :: Python
Classifier: Programming Language :: Python :: 2
Classifier: Programming Language :: Python :: 3
Classifier: Programming Language :: Python :: 3.4
Classifier: Topic :: Internet :: WWW/HTTP
Classifier: Topic :: Utilities
Classifier: Topic :: Software Development :: Libraries :: Python Modules
Classifier: License :: OSI Approved :: MIT License
